es_orm/es_helper.py
es_orm/helper.py
es_orm-0.1.5.dist-info/WHEEL
es_orm-0.1.5.dist-info/METADATA
es_orm-0.1.5.dist-info/RECORD
