Metadata-Version: 2.1
Name: es-orm
Version: 0.1.5
Summary: easy es helper
License: GPL
Author: iulmt
Author-email: 1817556010@qq.com
Requires-Python: >=3.6,<4.0
Classifier: License :: Other/Proprietary License
Classifier: Programming Language :: Python :: 3
Classifier: Programming Language :: Python :: 3.10
Classifier: Programming Language :: Python :: 3.6
Classifier: Programming Language :: Python :: 3.7
Classifier: Programming Language :: Python :: 3.8
Classifier: Programming Language :: Python :: 3.9
Requires-Dist: elasticsearch (==7.10.0)
